PyToneAnalyzer/__init__.py
PyToneAnalyzer/config.py
PyToneAnalyzer/config_manager.py
PyToneAnalyzer/fourier_math_utils.py
PyToneAnalyzer/general_display_utils.py
PyToneAnalyzer/general_functions_and_classes_utils.py
PyToneAnalyzer/io_utils.py
PyToneAnalyzer/waveform_plot_utils.py
PyToneAnalyzer/PyToneAnalyzer_data/instrument_samples/cello-c3_16_bit.wav
PyToneAnalyzer/PyToneAnalyzer_data/instrument_samples/clarinet-c5_16_bit.wav
PyToneAnalyzer/PyToneAnalyzer_data/instrument_samples/double-bass-c3_16_bit.wav
PyToneAnalyzer/PyToneAnalyzer_data/instrument_samples/female-vocal-c3_16_bit.wav
PyToneAnalyzer/PyToneAnalyzer_data/instrument_samples/flute-c6_16_bit.wav
PyToneAnalyzer/PyToneAnalyzer_data/instrument_samples/nylon-string-guitar-c4_16_bit.wav
PyToneAnalyzer/PyToneAnalyzer_data/instrument_samples/oboe-c4_16_bit.wav
PyToneAnalyzer/PyToneAnalyzer_data/instrument_samples/piano-c4_16_bit.wav
PyToneAnalyzer/PyToneAnalyzer_data/instrument_samples/piccolo-c6_16_bit.wav
PyToneAnalyzer/PyToneAnalyzer_data/instrument_samples/sax-alto-c5_16_bit.wav
PyToneAnalyzer/PyToneAnalyzer_data/instrument_samples/sax-baritone-c3_16_bit.wav
PyToneAnalyzer/PyToneAnalyzer_data/instrument_samples/sax-soprano-c5_16_bit.wav
PyToneAnalyzer/PyToneAnalyzer_data/instrument_samples/sax-tenor-c4_16_bit.wav
PyToneAnalyzer/PyToneAnalyzer_data/instrument_samples/steel-string-guitar-c4_16_bit.wav
PyToneAnalyzer/PyToneAnalyzer_data/instrument_samples/trombone-c4_16_bit.wav
PyToneAnalyzer/PyToneAnalyzer_data/instrument_samples/trumpet-c5_16_bit.wav
PyToneAnalyzer/PyToneAnalyzer_data/instrument_samples/violin-c5_16_bit.wav
PyToneAnalyzer-0.1.0.dist-info/LICENCE.txt
PyToneAnalyzer-0.1.0.dist-info/METADATA
PyToneAnalyzer-0.1.0.dist-info/WHEEL
PyToneAnalyzer-0.1.0.dist-info/top_level.txt
PyToneAnalyzer-0.1.0.dist-info/RECORD
